deno_provider/deno_provider.py
commitizen_deno_provider-1.0.0.dist-info/LICENSE.txt
commitizen_deno_provider-1.0.0.dist-info/METADATA
commitizen_deno_provider-1.0.0.dist-info/WHEEL
commitizen_deno_provider-1.0.0.dist-info/entry_points.txt
commitizen_deno_provider-1.0.0.dist-info/top_level.txt
commitizen_deno_provider-1.0.0.dist-info/RECORD
